sklPCA/__init__.py
sklPCA/functions.py
sklPCA-1.0.0.data/scripts/examples.py
sklPCA-1.0.0.dist-info/METADATA
sklPCA-1.0.0.dist-info/RECORD
sklPCA-1.0.0.dist-info/WHEEL
sklPCA-1.0.0.dist-info/top_level.txt
