Metadata-Version: 2.1
Name: sklPCA
Version: 1.0.0
Summary: Supervised Kernel-Based Longitudinal PCA (skl-PCA)
Home-page: http://mindstrong.com
Author: Mindstrong Health Data Science
Author-email: datascience@mindstronghealth.com
License: UNKNOWN
Keywords: digital biomarkers,supervised methods,kernel methods,longitudinal methods,dimension reduction,machine learning
Platform: UNKNOWN
Classifier: Development Status :: 5 - Production/Stable
Classifier: Intended Audience :: Developers
Classifier: License :: OSI Approved :: GNU Affero General Public License v3
Classifier: Programming Language :: Python :: 3
Requires-Dist: numpy
Requires-Dist: scipy
Requires-Dist: pandas
Requires-Dist: sklearn
